{
  "id": "4600240",
  "name": "tf",
  "font_family": "iconfont",
  "css_prefix_text": "icon-",
  "description": "",
  "glyphs": [
    {
      "icon_id": "984416",
      "name": "卖车",
      "font_class": "maiche",
      "unicode": "e6e9",
      "unicode_decimal": 59113
    },
    {
      "icon_id": "3060012",
      "name": "新车",
      "font_class": "xinche",
      "unicode": "e610",
      "unicode_decimal": 58896
    },
    {
      "icon_id": "25164578",
      "name": "二手车",
      "font_class": "ershouche",
      "unicode": "fd72",
      "unicode_decimal": 64882
    },
    {
      "icon_id": "33986999",
      "name": "首页-置灰",
      "font_class": "shouye-zhihui",
      "unicode": "e61d",
      "unicode_decimal": 58909
    }
  ]
}
